Workbook

Sheet Valuation>

Sheet Sensex Val
B5: Valuing the S&P BSE SENSEX | E5: =IF(OR(C8="",C9="",C10="",C11="",C12=""),"Provide Correct Inputs", SUM(E15:E25)) -> 91329.561
B6: Key Inputs | D6: Assumptions | E6: =IF(OR(C8="",C9="",C10="",C11="",C12=""),"Provide Correct Inputs", IF(E5>1.05*D8,"Undervalued",IF(E5<0.95*D8,"Overvalued","Fairly Valued"))) -> Undervalued
B7: Date | C7: =TODAY() -> 46111 | D7: =C7 -> 46111
B8: Current Sensex Level | C8: 73583.22 | D8: =C8 -> 73583.22 | E8: =IF(OR(C8="",C9="",C10="",C11="",C12=""),"Provide Correct Inputs","The market implied fair value of Sensex is "&ROUNDUP(E5,0)&". The Sensex is currently trading at "&ROUNDUP(D8,0)&". A "&TEXT(ABS((D8-E5)/D8),"0.00%"))&" "&IF(E6="Undervalued","appreciation",IF(E6="overvalued","correction","adjustment"))&" is expected from this level." -> The market implied fair value of Sensex is 91330. The Sensex is currently trading at 73584. A 24.12% appreciation is expected from this level.
B9: Total Yield | C9: 20 years | D9: =VLOOKUP(C9,'ExpDiv&BB'!K4:L14,2,0) -> 0.01290516
B10: Expected Growth | C10: 10 years | D10: =VLOOKUP(C10,SensexEPSGrowth!L4:M10,2,0) -> 0.10924129
B11: Risk-Free Rate | C11: Latest | D11: =VLOOKUP(C11,RfrHistorical!M4:N12,2,0) -> 0.06588
B12: Equity Risk Premium | C12: Latest | D12: =VLOOKUP(C12,ErpHistorical!F4:G10,2,0) -> 0.0167
B13: Cost of Equity | D13: =D11+D12 -> 0.08258
B14: Year | C14: Expected Dividends and Buybacks | D14: Cumulative PV Factor [ Risk-free Rate + Equity Risk Premium ] | E14: Present Value of Expected Dividends and Buybacks
B15: 2025 | C15: =$D$8*$D$9*(1+$D$10)^(B15-($B$15-1)) -> 1053.3391 | D15: =1/((1+($D$13))^(B15-($B$15-1))) -> 0.92371926 | E15: =C15*D15 -> 972.98959
B16: =B15+1 -> 2026 | C16: =$D$8*$D$9*(1+$D$10)^(B16-($B$15-1)) -> 1168.4072 | D16: =1/((1+($D$13))^(B16-($B$15-1))) -> 0.85325728 | E16: =C16*D16 -> 996.95194
B17: =B16+1 -> 2027 | C17: =$D$8*$D$9*(1+$D$10)^(B17-($B$15-1)) -> 1296.0455 | D17: =1/((1+($D$13))^(B17-($B$15-1))) -> 0.78817018 | E17: =C17*D17 -> 1021.5044
B18: =B17+1 -> 2028 | C18: =$D$8*$D$9*(1+$D$10)^(B18-($B$15-1)) -> 1437.6272 | D18: =1/((1+($D$13))^(B18-($B$15-1))) -> 0.72804798 | E18: =C18*D18 -> 1046.6616
B19: =B18+1 -> 2029 | C19: =$D$8*$D$9*(1+$D$10)^(B19-($B$15-1)) -> 1594.6754 | D19: =1/((1+($D$13))^(B19-($B$15-1))) -> 0.67251194 | E19: =C19*D19 -> 1072.4383
B20: =B19+1 -> 2030 | C20: =$D$8*$D$9*(1+$D$10)^(B20-($B$15-1)) -> 1768.8798 | D20: =1/((1+($D$13))^(B20-($B$15-1))) -> 0.62121224 | E20: =C20*D20 -> 1098.8498
B21: =B20+1 -> 2031 | C21: =$D$8*$D$9*(1+$D$10)^(B21-($B$15-1)) -> 1962.1146 | D21: =1/((1+($D$13))^(B21-($B$15-1))) -> 0.57382571 | E21: =C21*D21 -> 1125.9118
B22: =B21+1 -> 2032 | C22: =$D$8*$D$9*(1+$D$10)^(B22-($B$15-1)) -> 2176.4585 | D22: =1/((1+($D$13))^(B22-($B$15-1))) -> 0.53005386 | E22: =C22*D22 -> 1153.6402
B23: =B22+1 -> 2033 | C23: =$D$8*$D$9*(1+$D$10)^(B23-($B$15-1)) -> 2414.2176 | D23: =1/((1+($D$13))^(B23-($B$15-1))) -> 0.48962096 | E23: =C23*D23 -> 1182.0516
B24: =B23+1 -> 2034 | C24: =$D$8*$D$9*(1+$D$10)^(B24-($B$15-1)) -> 2677.9499 | D24: =1/((1+($D$13))^(B24-($B$15-1))) -> 0.45227232 | E24: =C24*D24 -> 1211.1626
B25: =B24&" - "&"ꝏ " -> 2034 - ꝏ | C25: =C24*(1+D10)/D12 -> 177873.81 | D25: =D24 -> 0.45227232 | E25: =C25*D25 -> 80447.399
J27: Total Yield | K27: EPS Growth | L27: Risk-fr rate | M27: ERP
J28: 20 years | K28: 10 years | L28: 20 years | M28: 15 years
J29: 15 years | K29: 7 years | L29: 15 years | M29: 7 years
J30: 10 years | K30: 5 years | L30: 7 years | M30: 5 years
J31: 7 years | K31: 3 years | L31: 5 years | M31: Latest
J32: 5 years | L32: Latest
J33: 3 years

Sheet Data>

Sheet ExpDiv&BB
B2: Year | C2: Sensex Average Range | D2: Dividend Yield | E2: Dividend Amount | F2: BB Amount | G2: Total Earnings | H2: Total Earning Yield
B3: 1998 | C3: 3300.7692 | D3: 0.0182 | E3: =D3*C3 -> 60.073999 | F3: =E3*'2025-BBData'!$J$8 -> 0.87447107 | G3: =E3+F3 -> 60.94847 | H3: =G3/C3 -> 0.018464929
B4: 1999 | C4: 4180.225 | D4: 0.0123 | E4: =D4*C4 -> 51.416767 | F4: =E4*'2025-BBData'!$J$8 -> 0.74845152 | G4: =E4+F4 -> 52.165219 | H4: =G4/C4 -> 0.012479046 | J4: Average Sensex Earning Yield- | K4: 20 years | L4: =AVERAGE(H10:H29) -> 0.01290516
B5: 2000 | C5: 4501.8467 | D5: 0.0125 | E5: =D5*C5 -> 56.273083 | F5: =E5*'2025-BBData'!$J$8 -> 0.81914279 | G5: =E5+F5 -> 57.092226 | H5: =G5/C5 -> 0.012681957
B6: 2001 | C6: 3475.9217 | D6: 0.0195 | E6: =D6*C6 -> 67.780473 | F6: =E6*'2025-BBData'!$J$8 -> 0.98665085 | G6: =E6+F6 -> 68.767123 | H6: =G6/C6 -> 0.019783853 | J6: Average Sensex Earning Yield- | K6: 15 years | L6: =AVERAGE(H15:H29) -> 0.012749594
B7: 2002 | C7: 3230.5783 | D7: 0.0221 | E7: =D7*C7 -> 71.395781 | F7: =E7*'2025-BBData'!$J$8 -> 1.0392773 | G7: =E7+F7 -> 72.435058 | H7: =G7/C7 -> 0.0224217
B8: 2003 | C8: 3967.6383 | D8: 0.0203 | E8: =D8*C8 -> 80.543058 | F8: =E8*'2025-BBData'!$J$8 -> 1.1724303 | G8: =E8+F8 -> 81.715488 | H8: =G8/C8 -> 0.020595498 | J8: Average Sensex Earning Yield- | K8: 10 years | L8: =AVERAGE(H20:H29) -> 0.012073223
B9: 2004 | C9: 5551.6008 | D9: 0.02 | E9: =D9*C9 -> 111.03202 | F9: =E9*'2025-BBData'!$J$8 -> 1.6162448 | G9: =E9+F9 -> 112.64826 | H9: =G9/C9 -> 0.020291131
B10: 2005 | C10: 7498.3675 | D10: 0.0148 | E10: =D10*C10 -> 110.97584 | F10: =E10*'2025-BBData'!$J$8 -> 1.615427 | G10: =E10+F10 -> 112.59127 | H10: =G10/C10 -> 0.015015437 | J10: Average Sensex Earning Yield- | K10: 7 years | L10: =AVERAGE(H23:H29) -> 0.011392021
B11: 2006 | C11: 11663.582 | D11: 0.0131 | E11: =D11*C11 -> 152.79292 | F11: =E11*'2025-BBData'!$J$8 -> 2.2241401 | G11: =E11+F11 -> 155.01706 | H11: =G11/C11 -> 0.013290691
B12: 2007 | C12: 15901.442 | D12: 0.0104 | E12: =D12*C12 -> 165.375 | F12: =E12*'2025-BBData'!$J$8 -> 2.407292 | G12: =E12+F12 -> 167.78229 | H12: =G12/C12 -> 0.010551388 | J12: Average Sensex Earning Yield- | K12: 5 years | L12: =AVERAGE(H25:H29) -> 0.011139831
B13: 2008 | C13: 14028.762 | D13: 0.0152 | E13: =D13*C13 -> 213.23719 | F13: =E13*'2025-BBData'!$J$8 -> 3.104001 | G13: =E13+F13 -> 216.34119 | H13: =G13/C13 -> 0.01542126
B14: 2009 | C14: 13941.483 | D14: 0.0124 | E14: =D14*C14 -> 172.87438 | F14: =E14*'2025-BBData'!$J$8 -> 2.5164572 | G14: =E14+F14 -> 175.39084 | H14: =G14/C14 -> 0.012580501 | J14: Average Sensex Earning Yield- | K14: 3 years | L14: =AVERAGE(H27:H29) -> 0.012073223
B15: 2010 | C15: 18207.561 | D15: 0.0111 | E15: =D15*C15 -> 202.10393 | F15: =E15*'2025-BBData'!$J$8 -> 2.9419389 | G15: =E15+F15 -> 205.04586 | H15: =G15/C15 -> 0.011261578
B16: 2011 | C16: 17724.383 | D16: 0.0141 | E16: =D16*C16 -> 249.91379 | F16: =E16*'2025-BBData'!$J$8 -> 3.6378864 | G16: =E16+F16 -> 253.55168 | H16: =G16/C16 -> 0.014305248
B17: 2012 | C17: 17834.852 | D17: 0.0164 | E17: =D17*C17 -> 292.49157 | F17: =E17*'2025-BBData'!$J$8 -> 4.2576725 | G17: =E17+F17 -> 296.74924 | H17: =G17/C17 -> 0.016638728
B18: 2013 | C18: 19727.075 | D18: 0.015 | E18: =D18*C18 -> 295.90612 | F18: =E18*'2025-BBData'!$J$8 -> 4.3073767 | G18: =E18+F18 -> 300.2135 | H18: =G18/C18 -> 0.015218348
B19: 2014 | C19: 24940.999 | D19: 0.0129 | E19: =D19*C19 -> 321.73889 | F19: =E19*'2025-BBData'!$J$8 -> 4.683413 | G19: =E19+F19 -> 326.4223 | H19: =G19/C19 -> 0.01308778
B20: 2015 | C20: 27382.92 | D20: 0.0139 | E20: =D20*C20 -> 380.62259 | F20: =E20*'2025-BBData'!$J$8 -> 5.5405574 | G20: =E20+F20 -> 386.16315 | H20: =G20/C20 -> 0.014102336
B21: 2016 | C21: 26505.693 | D21: 0.0143 | E21: =D21*C21 -> 379.03141 | F21: =E21*'2025-BBData'!$J$8 -> 5.5173954 | G21: =E21+F21 -> 384.54881 | H21: =G21/C21 -> 0.014508159
B22: 2017 | C22: 31162.837 | D22: 0.0122 | E22: =D22*C22 -> 380.18662 | F22: =E22*'2025-BBData'!$J$8 -> 5.5342112 | G22: =E22+F22 -> 385.72083 | H22: =G22/C22 -> 0.01237759
B23: 2018 | C23: 35683.952 | D23: 0.0119 | E23: =D23*C23 -> 424.63903 | F23: =E23*'2025-BBData'!$J$8 -> 6.1812857 | G23: =E23+F23 -> 430.82032 | H23: =G23/C23 -> 0.012073223
B24: 2019 | C24: 38716.272 | D24: 0.0118 | E24: =D24*C24 -> 456.85202 | F24: =E24*'2025-BBData'!$J$8 -> 6.650196 | G24: =E24+F24 -> 463.50221 | H24: =G24/C24 -> 0.011971767
B25: 2020 | C25: 37947.085 | D25: 0.0098 | E25: =D25*C25 -> 371.88143 | F25: =E25*'2025-BBData'!$J$8 -> 5.4133162 | G25: =E25+F25 -> 377.29475 | H25: =G25/C25 -> 0.0099426543
B26: 2021 | C26: 53499.052 | D26: 0.0094 | E26: =D26*C26 -> 502.89109 | F26: =E26*'2025-BBData'!$J$8 -> 7.3203669 | G26: =E26+F26 -> 510.21146 | H26: =G26/C26 -> 0.0095368317
... B29: 2024 | C29: 77593.194 | D29: 0.0116 | E29: =D29*C29 -> 900.08105 | F29: =E29*'2025-BBData'!$J$8 -> 13.102088 | G29: =E29+F29 -> 913.18314 | H29: =G29/C29 -> 0.011768856

Sheet SensexEPSGrowth
B2: Year | C2: Sensex Average Range | D2: PE Ratios | E2: Sensex EPS | F2: EPS CAGR 3 Years | G2: EPS CAGR 5 Years | H2: EPS CAGR 7 Years | I2: EPS CAGR 10 Years | P2: Year | Q2: Close | R2: PE Ratios | S2: PB Ratios | T2: Dividend Yield
B3: 1998 | C3: =IFERROR(SensexHistorical!G3,0) -> 3300.7692 | D3: =IFERROR(R3,0) -> 12.86 | E3: =C3/D3 -> 256.66945 | F3: - | G3: - | H3: - | I3: - | P3: 1998 | Q3: 3739.96 | R3: 12.86 | S3: 2.26 | T3: 1.82
B4: =B3+1 -> 1999 | C4: =IFERROR(SensexHistorical!G4,0) -> 4180.225 | D4: =IFERROR(R4,0) -> 19.76 | E4: =C4/D4 -> 211.54985 | F4: - | G4: - | H4: - | I4: - | K4: Average EPS CAGR- | L4: 10 years | M4: =AVERAGE(I13:I29) -> 0.10924129 | P4: 1999 | Q4: 5001.28 | R4: 19.76 | S4: 3.4 | T4: 1.23
B5: =B4+1 -> 2000 | C5: =IFERROR(SensexHistorical!G5,0) -> 4501.8467 | D5: =IFERROR(R5,0) -> 23.89 | E5: =C5/D5 -> 188.44063 | F5: - | G5: - | H5: - | I5: - | P5: 2000 | Q5: 3604.38 | R5: 23.89 | S5: 3.6 | T5: 1.25
B6: =B5+1 -> 2001 | C6: =IFERROR(SensexHistorical!G6,0) -> 3475.9217 | D6: =IFERROR(R6,0) -> 16.55 | E6: =C6/D6 -> 210.02548 | F6: =_xlfn.RRI(3,E3,E6) -> -0.064667699 | G6: - | H6: - | I6: - | K6: Average EPS CAGR- | L6: 7 years | M6: =AVERAGE(H10:H29) -> 0.11403739 | P6: 2001 | Q6: 3469.35 | R6: 16.55 | S6: 2.38 | T6: 1.95
B7: =B6+1 -> 2002 | C7: =IFERROR(SensexHistorical!G7,0) -> 3230.5783 | D7: =IFERROR(R7,0) -> 14.51 | E7: =C7/D7 -> 222.64496 | F7: =_xlfn.RRI(3,E4,E7) -> 0.017185237 | G7: - | H7: - | I7: - | P7: 2002 | Q7: 3048.72 | R7: 14.51 | S7: 2.23 | T7: 2.21
B8: =B7+1 -> 2003 | C8: =IFERROR(SensexHistorical!G8,0) -> 3967.6383 | D8: =IFERROR(R8,0) -> 16.18 | E8: =C8/D8 -> 245.21869 | F8: =_xlfn.RRI(3,E5,E8) -> 0.091757885 | G8: =_xlfn.RRI(5,E3,E8) -> -0.0090862038 | H8: - | I8: - | K8: Average EPS CAGR- | L8: 5 years | M8: =AVERAGE(G8:G29) -> 0.11441846 | P8: 2003 | Q8: 5590.6 | R8: 16.18 | S8: 2.82 | T8: 2.03
B9: =B8+1 -> 2004 | C9: =IFERROR(SensexHistorical!G9,0) -> 5551.6008 | D9: =IFERROR(R9,0) -> 16.56 | E9: =C9/D9 -> 335.2416 | F9: =_xlfn.RRI(3,E6,E9) -> 0.16867918 | G9: =_xlfn.RRI(5,E4,E9) -> 0.096450516 | H9: - | I9: - | P9: 2004 | Q9: 6492.82 | R9: 16.56 | S9: 3.32 | T9: 2
B10: =B9+1 -> 2005 | C10: =IFERROR(SensexHistorical!G10,0) -> 7498.3675 | D10: =IFERROR(R10,0) -> 16.98 | E10: =C10/D10 -> 441.59997 | F10: =_xlfn.RRI(3,E7,E10) -> 0.25643123 | G10: =_xlfn.RRI(5,E5,E10) -> 0.18568929 | H10: =_xlfn.RRI(7,E3,E10) -> 0.080600038 | I10: - | K10: Average EPS CAGR- | L10: 3 years | M10: =AVERAGE(F6:F29) -> 0.11747281 | P10: 2005 | Q10: 11279.96 | R10: 16.98 | S10: 4.16 | T10: 1.48
B11: =B10+1 -> 2006 | C11: =IFERROR(SensexHistorical!G11,0) -> 11663.582 | D11: =IFERROR(R11,0) -> 20.72 | E11: =C11/D11 -> 562.91417 | F11: =_xlfn.RRI(3,E8,E11) -> 0.31915615 | G11: =_xlfn.RRI(5,E6,E11) -> 0.21796285 | H11: =_xlfn.RRI(7,E4,E11) -> 0.15005469 | I11: - | P11: 2006 | Q11: 13072.1 | R11: 20.72 | S11: 4.88 | T11: 1.31
B12: =B11+1 -> 2007 | C12: =IFERROR(SensexHistorical!G12,0) -> 15901.442 | D12: =IFERROR(R12,0) -> 22.61 | E12: =C12/D12 -> 703.29246 | F12: =_xlfn.RRI(3,E9,E12) -> 0.28014556 | G12: =_xlfn.RRI(5,E7,E12) -> 0.25864895 | H12: =_xlfn.RRI(7,E5,E12) -> 0.20700418 | I12: - | P12: 2007 | Q12: 15644.44 | R12: 22.61 | S12: 5.47 | T12: 1.04
B13: =B12+1 -> 2008 | C13: =IFERROR(SensexHistorical!G13,0) -> 14028.762 | D13: =IFERROR(R13,0) -> 15.66 | E13: =C13/D13 -> 895.83413 | F13: =_xlfn.RRI(3,E10,E13) -> 0.26590036 | G13: =_xlfn.RRI(5,E8,E13) -> 0.29579055 | H13: =_xlfn.RRI(7,E6,E13) -> 0.23025081 | I13: =_xlfn.RRI(10,E3,E13) -> 0.13314462 | P13: 2008 | Q13: 9708.5 | R13: 15.66 | S13: 3.38 | T13: 1.52
B14: =B13+1 -> 2009 | C14: =IFERROR(SensexHistorical!G14,0) -> 13941.483 | D14: =IFERROR(R14,0) -> 20.13 | E14: =C14/D14 -> 692.5724 | F14: =_xlfn.RRI(3,E11,E14) -> 0.071538221 | G14: =_xlfn.RRI(5,E9,E14) -> 0.15616936 | H14: =_xlfn.RRI(7,E7,E14) -> 0.17600041 | I14: =_xlfn.RRI(10,E4,E14) -> 0.12591407 | P14: 2009 | Q14: 17527.77 | R14: 20.13 | S14: 3.75 | T14: 1.24
B15: =B14+1 -> 2010 | C15: =IFERROR(SensexHistorical!G15,0) -> 18207.561 | D15: =IFERROR(R15,0) -> 21.6 | E15: =C15/D15 -> 842.94263 | F15: =_xlfn.RRI(3,E12,E15) -> 0.062235193 | G15: =_xlfn.RRI(5,E10,E15) -> 0.13803022 | H15: =_xlfn.RRI(7,E8,E15) -> 0.19290635 | I15: =_xlfn.RRI(10,E5,E15) -> 0.16161536 | P15: 2010 | Q15: 19445.22 | R15: 21.6 | S15: 3.58 | T15: 1.11
B16: =B15+1 -> 2011 | C16: =IFERROR(SensexHistorical!G16,0) -> 17724.383 | D16: =IFERROR(R16,0) -> 18.5 | E16: =C16/D16 -> 958.07473 | F16: =_xlfn.RRI(3,E13,E16) -> 0.02264271 | G16: =_xlfn.RRI(5,E11,E16) -> 0.1122219 | H16: =_xlfn.RRI(7,E9,E16) -> 0.16184658 | I16: =_xlfn.RRI(10,E6,E16) -> 0.16389215 | P16: 2011 | Q16: 17404.2 | R16: 18.5 | S16: 3.42 | T16: 1.41
B17: =B16+1 -> 2012 | C17: =IFERROR(SensexHistorical!G17,0) -> 17834.852 | D17: =IFERROR(R17,0) -> 17.09 | E17: =C17/D17 -> 1043.5841 | F17: =_xlfn.RRI(3,E14,E17) -> 0.14644727 | G17: =_xlfn.RRI(5,E12,E17) -> 0.082127156 | H17: =_xlfn.RRI(7,E10,E17) -> 0.13072479 | I17: =_xlfn.RRI(10,E7,E17) -> 0.16705536 | P17: 2012 | Q17: 18835.77 | R17: 17.09 | S17: 2.97 | T17: 1.64
B18: =B17+1 -> 2013 | C18: =IFERROR(SensexHistorical!G18,0) -> 19727.075 | D18: =IFERROR(R18,0) -> 17.38 | E18: =C18/D18 -> 1135.0446 | F18: =_xlfn.RRI(3,E15,E18) -> 0.10426075 | G18: =_xlfn.RRI(5,E13,E18) -> 0.048472548 | H18: =_xlfn.RRI(7,E11,E18) -> 0.10537619 | I18: =_xlfn.RRI(10,E8,E18) -> 0.16559033 | P18: 2013 | Q18: 22386.27 | R18: 17.38 | S18: 2.78 | T18: 1.5
B19: =B18+1 -> 2014 | C19: =IFERROR(SensexHistorical!G19,0) -> 24940.999 | D19: =IFERROR(R19,0) -> 18.73 | E19: =C19/D19 -> 1331.607 | F19: =_xlfn.RRI(3,E16,E19) -> 0.11598638 | G19: =_xlfn.RRI(5,E14,E19) -> 0.13967803 | H19: =_xlfn.RRI(7,E12,E19) -> 0.095483221 | I19: =_xlfn.RRI(10,E9,E19) -> 0.14789408 | P19: 2014 | Q19: 27957.49 | R19: 18.73 | S19: 2.94 | T19: 1.29
B20: =B19+1 -> 2015 | C20: =IFERROR(SensexHistorical!G20,0) -> 27382.92 | D20: =IFERROR(R20,0) -> 20.18 | E20: =C20/D20 -> 1356.9336 | F20: =_xlfn.RRI(3,E17,E20) -> 0.091466437 | G20: =_xlfn.RRI(5,E15,E20) -> 0.099897248 | H20: =_xlfn.RRI(7,E13,E20) -> 0.061112841 | I20: =_xlfn.RRI(10,E10,E20) -> 0.11880128 | P20: 2015 | Q20: 25341.86 | R20: 20.18 | S20: 2.85 | T20: 1.39
B21: =B20+1 -> 2016 | C21: =IFERROR(SensexHistorical!G21,0) -> 26505.693 | D21: =IFERROR(R21,0) -> 20.62 | E21: =C21/D21 -> 1285.4361 | F21: =_xlfn.RRI(3,E18,E21) -> 0.042347498 | G21: =_xlfn.RRI(5,E16,E21) -> 0.060547744 | H21: =_xlfn.RRI(7,E14,E21) -> 0.092368912 | I21: =_xlfn.RRI(10,E11,E21) -> 0.08607754 | P21: 2016 | Q21: 29620.5 | R21: 20.62 | S21: 2.84 | T21: 1.43
B22: =B21+1 -> 2017 | C22: =IFERROR(SensexHistorical!G22,0) -> 31162.837 | D22: =IFERROR(R22,0) -> 23.78 | E22: =C22/D22 -> 1310.4642 | F22: =_xlfn.RRI(3,E19,E22) -> -0.0053208266 | G22: =_xlfn.RRI(5,E17,E22) -> 0.046597134 | H22: =_xlfn.RRI(7,E15,E22) -> 0.065063015 | I22: =_xlfn.RRI(10,E12,E22) -> 0.064213879 | P22: 2017 | Q22: 32968.68 | R22: 23.78 | S22: 3.05 | T22: 1.22
B23: =B22+1 -> 2018 | C23: =IFERROR(SensexHistorical!G23,0) -> 35683.952 | D23: =IFERROR(R23,0) -> 23.71 | E23: =C23/D23 -> 1505.017 | F23: =_xlfn.RRI(3,E20,E23) -> 0.035128504 | G23: =_xlfn.RRI(5,E18,E23) -> 0.05804879 | H23: =_xlfn.RRI(7,E16,E23) -> 0.066645947 | I23: =_xlfn.RRI(10,E13,E23) -> 0.053249785 | P23: 2018 | Q23: 38672.91 | R23: 23.71 | S23: 3.03 | T23: 1.19
B24: =B23+1 -> 2019 | C24: =IFERROR(SensexHistorical!G24,0) -> 38716.272 | D24: =IFERROR(R24,0) -> 26.44 | E24: =C24/D24 -> 1464.3068 | F24: =_xlfn.RRI(3,E21,E24) -> 0.044384761 | G24: =_xlfn.RRI(5,E19,E24) -> 0.019180729 | H24: =_xlfn.RRI(7,E17,E24) -> 0.049578558 | I24: =_xlfn.RRI(10,E14,E24) -> 0.077746672 | P24: 2019 | Q24: 29468.49 | R24: 26.44 | S24: 2.95 | T24: 1.18
... B29: =B28+1 -> 2024 | C29: =IFERROR(SensexHistorical!G29,0) -> 77593.194 | D29: =IFERROR(R29,0) -> 23.2 | E29: =C29/D29 -> 3344.5342 | F29: =_xlfn.RRI(3,E26,E29) -> 0.22673569 | G29: =_xlfn.RRI(5,E24,E29) -> 0.17961615 | H29: =_xlfn.RRI(7,E22,E29) -> 0.14322068 | I29: =_xlfn.RRI(10,E19,E29) -> 0.09646799 | P29: 2024 | Q29: 77414.92 | R29: 23.2 | S29: 3.95 | T29: 1.16
P30: 2025 | Q30: 79809.65 | R30: 22.78 | S30: 4.23 | T30: 1.13

Sheet SensexHistorical
B2: Month | C2: Closing Price | D2: Monthly Returns | F2: Year | G2: Sensex Average Range | H2: Average Returns
B3: 35796 | C3: 3224.36 | D3: - | F3: 1998 | G3: =AVERAGEIFS($C$3:$C$332,$B$3:$B$332,">="&DATE(F3,1,1),$B$3:$B$332,"<="&DATE(F3,12,31)) -> 3300.7692 | H3: -
B4: 35827 | C4: 3622.22 | D4: =C4/C3-1 -> 0.12339193 | F4: =F3+1 -> 1999 | G4: =AVERAGEIFS($C$3:$C$332,$B$3:$B$332,">="&DATE(F4,1,1),$B$3:$B$332,"<="&DATE(F4,12,31)) -> 4180.225 | H4: =G4/G3-1 -> 0.26643967 | J4: CAGR Sensex Returns- | K4: 20 years | L4: =_xlfn.RRI(20,G10,G29) -> 0.12393927
B5: 35855 | C5: 3892.75 | D5: =C5/C4-1 -> 0.074686242 | F5: =F4+1 -> 2000 | G5: =AVERAGEIFS($C$3:$C$332,$B$3:$B$332,">="&DATE(F5,1,1),$B$3:$B$332,"<="&DATE(F5,12,31)) -> 4501.8467 | H5: =G5/G4-1 -> 0.076938841
B6: 35886 | C6: 4006.81 | D6: =C6/C5-1 -> 0.029300623 | F6: =F5+1 -> 2001 | G6: =AVERAGEIFS($C$3:$C$332,$B$3:$B$332,">="&DATE(F6,1,1),$B$3:$B$332,"<="&DATE(F6,12,31)) -> 3475.9217 | H6: =G6/G5-1 -> -0.22788981 | J6: CAGR Sensex Returns- | K6: 15 years | L6: =_xlfn.RRI(15,G16,G29) -> 0.10344367
B7: 35916 | C7: 3686.39 | D7: =C7/C6-1 -> -0.079968853 | F7: =F6+1 -> 2002 | G7: =AVERAGEIFS($C$3:$C$332,$B$3:$B$332,">="&DATE(F7,1,1),$B$3:$B$332,"<="&DATE(F7,12,31)) -> 3230.5783 | H7: =G7/G6-1 -> -0.070583677
B8: 35947 | C8: 3250.69 | D8: =C8/C7-1 -> -0.11819151 | F8: =F7+1 -> 2003 | G8: =AVERAGEIFS($C$3:$C$332,$B$3:$B$332,">="&DATE(F8,1,1),$B$3:$B$332,"<="&DATE(F8,12,31)) -> 3967.6383 | H8: =G8/G7-1 -> 0.2281511 | J8: CAGR Sensex Returns- | K8: 10 years | L8: =_xlfn.RRI(10,G20,G29) -> 0.10977359
B9: 35977 | C9: 3211.31 | D9: =C9/C8-1 -> -0.012114351 | F9: =F8+1 -> 2004 | G9: =AVERAGEIFS($C$3:$C$332,$B$3:$B$332,">="&DATE(F9,1,1),$B$3:$B$332,"<="&DATE(F9,12,31)) -> 5551.6008 | H9: =G9/G8-1 -> 0.39922049
B10: 36008 | C10: 2933.85 | D10: =C10/C9-1 -> -0.086400877 | F10: =F9+1 -> 2005 | G10: =AVERAGEIFS($C$3:$C$332,$B$3:$B$332,">="&DATE(F10,1,1),$B$3:$B$332,"<="&DATE(F10,12,31)) -> 7498.3675 | H10: =G10/G9-1 -> 0.35066762 | J10: CAGR Sensex Returns- | K10: 7 years | L10: =_xlfn.RRI(7,G23,G29) -> 0.11735957
B11: 36039 | C11: 3102.29 | D11: =C11/C10-1 -> 0.057412615 | F11: =F10+1 -> 2006 | G11: =AVERAGEIFS($C$3:$C$332,$B$3:$B$332,">="&DATE(F11,1,1),$B$3:$B$332,"<="&DATE(F11,12,31)) -> 11663.582 | H11: =G11/G10-1 -> 0.5554828
B12: 36069 | C12: 2812.49 | D12: =C12/C11-1 -> -0.093414865 | F12: =F11+1 -> 2007 | G12: =AVERAGEIFS($C$3:$C$332,$B$3:$B$332,">="&DATE(F12,1,1),$B$3:$B$332,"<="&DATE(F12,12,31)) -> 15901.442 | H12: =G12/G11-1 -> 0.36334129 | J12: CAGR Sensex Returns- | K12: 5 years | L12: =_xlfn.RRI(5,G25,G29) -> 0.15379603
B13: 36100 | C13: 2810.66 | D13: =C13/C12-1 -> -0.00065066898 | F13: =F12+1 -> 2008 | G13: =AVERAGEIFS($C$3:$C$332,$B$3:$B$332,">="&DATE(F13,1,1),$B$3:$B$332,"<="&DATE(F13,12,31)) -> 14028.762 | H13: =G13/G12-1 -> -0.11776793
B14: 36130 | C14: 3055.41 | D14: =C14/C13-1 -> 0.087079191 | F14: =F13+1 -> 2009 | G14: =AVERAGEIFS($C$3:$C$332,$B$3:$B$332,">="&DATE(F14,1,1),$B$3:$B$332,"<="&DATE(F14,12,31)) -> 13941.483 | H14: =G14/G13-1 -> -0.0062215039
B15: 36161 | C15: 3315.57 | D15: =C15/C14-1 -> 0.085147329 | F15: =F14+1 -> 2010 | G15: =AVERAGEIFS($C$3:$C$332,$B$3:$B$332,">="&DATE(F15,1,1),$B$3:$B$332,"<="&DATE(F15,12,31)) -> 18207.561 | H15: =G15/G14-1 -> 0.3059989
B16: 36192 | C16: 3399.63 | D16: =C16/C15-1 -> 0.025353107 | F16: =F15+1 -> 2011 | G16: =AVERAGEIFS($C$3:$C$332,$B$3:$B$332,">="&DATE(F16,1,1),$B$3:$B$332,"<="&DATE(F16,12,31)) -> 17724.383 | H16: =G16/G15-1 -> -0.026537236
B17: 36220 | C17: 3739.96 | D17: =C17/C16-1 -> 0.10010795 | F17: =F16+1 -> 2012 | G17: =AVERAGEIFS($C$3:$C$332,$B$3:$B$332,">="&DATE(F17,1,1),$B$3:$B$332,"<="&DATE(F17,12,31)) -> 17834.852 | H17: =G17/G16-1 -> 0.0062326102
B18: 36251 | C18: 3325.69 | D18: =C18/C17-1 -> -0.11076856 | F18: =F17+1 -> 2013 | G18: =AVERAGEIFS($C$3:$C$332,$B$3:$B$332,">="&DATE(F18,1,1),$B$3:$B$332,"<="&DATE(F18,12,31)) -> 19727.075 | H18: =G18/G17-1 -> 0.10609695
B19: 36281 | C19: 3963.56 | D19: =C19/C18-1 -> 0.1918008 | F19: =F18+1 -> 2014 | G19: =AVERAGEIFS($C$3:$C$332,$B$3:$B$332,">="&DATE(F19,1,1),$B$3:$B$332,"<="&DATE(F19,12,31)) -> 24940.999 | H19: =G19/G18-1 -> 0.26430295
B20: 36312 | C20: 4140.73 | D20: =C20/C19-1 -> 0.044699714 | F20: =F19+1 -> 2015 | G20: =AVERAGEIFS($C$3:$C$332,$B$3:$B$332,">="&DATE(F20,1,1),$B$3:$B$332,"<="&DATE(F20,12,31)) -> 27382.92 | H20: =G20/G19-1 -> 0.097907899
B21: 36342 | C21: 4542.34 | D21: =C21/C20-1 -> 0.096990144 | F21: =F20+1 -> 2016 | G21: =AVERAGEIFS($C$3:$C$332,$B$3:$B$332,">="&DATE(F21,1,1),$B$3:$B$332,"<="&DATE(F21,12,31)) -> 26505.693 | H21: =G21/G20-1 -> -0.032035541
B22: 36373 | C22: 4898.21 | D22: =C22/C21-1 -> 0.078345082 | F22: =F21+1 -> 2017 | G22: =AVERAGEIFS($C$3:$C$332,$B$3:$B$332,">="&DATE(F22,1,1),$B$3:$B$332,"<="&DATE(F22,12,31)) -> 31162.837 | H22: =G22/G21-1 -> 0.17570354
B23: 36404 | C23: 4764.42 | D23: =C23/C22-1 -> -0.02731406 | F23: =F22+1 -> 2018 | G23: =AVERAGEIFS($C$3:$C$332,$B$3:$B$332,">="&DATE(F23,1,1),$B$3:$B$332,"<="&DATE(F23,12,31)) -> 35683.952 | H23: =G23/G22-1 -> 0.14508034
B24: 36434 | C24: 4444.56 | D24: =C24/C23-1 -> -0.067135139 | F24: =F23+1 -> 2019 | G24: =AVERAGEIFS($C$3:$C$332,$B$3:$B$332,">="&DATE(F24,1,1),$B$3:$B$332,"<="&DATE(F24,12,31)) -> 38716.272 | H24: =G24/G23-1 -> 0.084977134
... B29: 36586 | C29: 5001.28 | D29: =C29/C28-1 -> -0.081825158 | F29: =F28+1 -> 2024 | G29: =AVERAGEIFS($C$3:$C$332,$B$3:$B$332,">="&DATE(F29,1,1),$B$3:$B$332,"<="&DATE(F29,12,31)) -> 77593.194 | H29: =G29/G28-1 -> 0.21516591
B30: 36617 | C30: 4657.55 | D30: =C30/C29-1 -> -0.068728406
B31: 36647 | C31: 4433.61 | D31: =C31/C30-1 -> -0.048081073
B32: 36678 | C32: 4748.77 | D32: =C32/C31-1 -> 0.071084286
B33: 36708 | C33: 4279.86 | D33: =C33/C32-1 -> -0.098743464
B34: 36739 | C34: 4477.31 | D34: =C34/C33-1 -> 0.046134687
B35: 36770 | C35: 4090.38 | D35: =C35/C34-1 -> -0.086420194
B36: 36800 | C36: 3711.02 | D36: =C36/C35-1 -> -0.092744439
B37: 36831 | C37: 3997.99 | D37: =C37/C36-1 -> 0.077329144
B38: 36861 | C38: 3972.12 | D38: =C38/C37-1 -> -0.0064707516
B39: 36892 | C39: 4326.72 | D39: =C39/C38-1 -> 0.089272227
B40: 36923 | C40: 4247.04 | D40: =C40/C39-1 -> -0.018415798
B41: 36951 | C41: 3604.38 | D41: =C41/C40-1 -> -0.15131951
... B334: 45870 | C334: 79809.65 | D334: =C334/C333-1 -> -0.01694796
B336: Source: BSE

Sheet RfrHistorical
B2: Date | C2: Close | D2: Open | E2: High | F2: Low | G2: Change % | I2: Year | J2: 10Y Bond Average Range
B3: 45870 | C3: 0.06588 | D3: 0.06378 | E3: 0.0665 | F3: 0.06307 | G3: 0.0332 | I3: 1998 | J3: =AVERAGEIFS($C$3:$C$332,$B$3:$B$332,">="&DATE(I3,1,1),$B$3:$B$332,"<="&DATE(I3,12,31)) -> 0.121497
B4: 45839 | C4: 0.06376 | D4: 0.0629 | E4: 0.0637 | F4: 0.0628 | G4: 0.0095 | I4: =I3+1 -> 1999 | J4: =AVERAGEIFS($C$3:$C$332,$B$3:$B$332,">="&DATE(I4,1,1),$B$3:$B$332,"<="&DATE(I4,12,31)) -> 0.11739167 | L4: Average Rate- | M4: 20 years | N4: =AVERAGE(J10:J29) -> 0.074284375
B5: 45809 | C5: 0.06316 | D5: 0.0622 | E5: 0.0631 | F5: 0.0618 | G5: 0.0171 | I5: =I4+1 -> 2000 | J5: =AVERAGEIFS($C$3:$C$332,$B$3:$B$332,">="&DATE(I5,1,1),$B$3:$B$332,"<="&DATE(I5,12,31)) -> 0.11044917
B6: 45778 | C6: 0.0621 | D6: 0.0635 | E6: 0.0639 | F6: 0.0616 | G6: -0.0224 | I6: =I5+1 -> 2001 | J6: =AVERAGEIFS($C$3:$C$332,$B$3:$B$332,">="&DATE(I6,1,1),$B$3:$B$332,"<="&DATE(I6,12,31)) -> 0.093700833 | L6: Average Rate- | M6: 15 years | N6: =AVERAGE(J15:J29) -> 0.074119167
B7: 45748 | C7: 0.06352 | D7: 0.0657 | E7: 0.0657 | F7: 0.0631 | G7: -0.0332 | I7: =I6+1 -> 2002 | J7: =AVERAGEIFS($C$3:$C$332,$B$3:$B$332,">="&DATE(I7,1,1),$B$3:$B$332,"<="&DATE(I7,12,31)) -> 0.0719525
B8: 45717 | C8: 0.0657 | D8: 0.0673 | E8: 0.0674 | F8: 0.0657 | G8: -0.0223 | I8: =I7+1 -> 2003 | J8: =AVERAGEIFS($C$3:$C$332,$B$3:$B$332,">="&DATE(I8,1,1),$B$3:$B$332,"<="&DATE(I8,12,31)) -> 0.0560475 | L8: Average Rate- | M8: 7 years | N8: =AVERAGE(J23:J29) -> 0.068922262
B9: 45689 | C9: 0.0672 | D9: 0.0666 | E9: 0.0672 | F9: 0.0665 | G9: 0.0045 | I9: =I8+1 -> 2004 | J9: =AVERAGEIFS($C$3:$C$332,$B$3:$B$332,">="&DATE(I9,1,1),$B$3:$B$332,"<="&DATE(I9,12,31)) -> 0.059314167
B10: 45658 | C10: 0.0669 | D10: 0.0678 | E10: 0.0684 | F10: 0.0667 | G10: -0.0104 | I10: =I9+1 -> 2005 | J10: =AVERAGEIFS($C$3:$C$332,$B$3:$B$332,">="&DATE(I10,1,1),$B$3:$B$332,"<="&DATE(I10,12,31)) -> 0.06971 | L10: Average Rate- | M10: 5 years | N10: =AVERAGE(J25:J29) -> 0.067216333
B11: 45627 | C11: 0.0676 | D11: 0.06802 | E11: 0.06807 | F11: 0.06668 | G11: 0.0013 | I11: =I10+1 -> 2006 | J11: =AVERAGEIFS($C$3:$C$332,$B$3:$B$332,">="&DATE(I11,1,1),$B$3:$B$332,"<="&DATE(I11,12,31)) -> 0.076628333
B12: 45597 | C12: 0.06751 | D12: 0.06831 | E12: 0.06863 | F12: 0.06739 | G12: -0.0132 | I12: =I11+1 -> 2007 | J12: =AVERAGEIFS($C$3:$C$332,$B$3:$B$332,">="&DATE(I12,1,1),$B$3:$B$332,"<="&DATE(I12,12,31)) -> 0.079529167 | L12: Average Rate- | M12: Latest | N12: =C3 -> 0.06588
B13: 45566 | C13: 0.06841 | D13: 0.06759 | E13: 0.06875 | F13: 0.0673 | G13: 0.0135 | I13: =I12+1 -> 2008 | J13: =AVERAGEIFS($C$3:$C$332,$B$3:$B$332,">="&DATE(I13,1,1),$B$3:$B$332,"<="&DATE(I13,12,31)) -> 0.078546667
B14: 45536 | C14: 0.0675 | D14: 0.06877 | E14: 0.06885 | F14: 0.06706 | G14: -0.0165 | I14: =I13+1 -> 2009 | J14: =AVERAGEIFS($C$3:$C$332,$B$3:$B$332,">="&DATE(I14,1,1),$B$3:$B$332,"<="&DATE(I14,12,31)) -> 0.069485833
B15: 45505 | C15: 0.06863 | D15: 0.06912 | E15: 0.06919 | F15: 0.06843 | G15: -0.0088 | I15: =I14+1 -> 2010 | J15: =AVERAGEIFS($C$3:$C$332,$B$3:$B$332,">="&DATE(I15,1,1),$B$3:$B$332,"<="&DATE(I15,12,31)) -> 0.078485
B16: 45474 | C16: 0.06924 | D16: 0.07023 | E16: 0.07024 | F16: 0.0691 | G16: -0.012 | I16: =I15+1 -> 2011 | J16: =AVERAGEIFS($C$3:$C$332,$B$3:$B$332,">="&DATE(I16,1,1),$B$3:$B$332,"<="&DATE(I16,12,31)) -> 0.0836575
B17: 45444 | C17: 0.07008 | D17: 0.06955 | E17: 0.07062 | F17: 0.06945 | G17: 0.0031 | I17: =I16+1 -> 2012 | J17: =AVERAGEIFS($C$3:$C$332,$B$3:$B$332,">="&DATE(I17,1,1),$B$3:$B$332,"<="&DATE(I17,12,31)) -> 0.08295
B18: 45413 | C18: 0.06986 | D18: 0.0717 | E18: 0.07173 | F18: 0.06967 | G18: -0.029 | I18: =I17+1 -> 2013 | J18: =AVERAGEIFS($C$3:$C$332,$B$3:$B$332,">="&DATE(I18,1,1),$B$3:$B$332,"<="&DATE(I18,12,31)) -> 0.081975833
B19: 45383 | C19: 0.07195 | D19: 0.07085 | E19: 0.07242 | F19: 0.07075 | G19: 0.0203 | I19: =I18+1 -> 2014 | J19: =AVERAGEIFS($C$3:$C$332,$B$3:$B$332,">="&DATE(I19,1,1),$B$3:$B$332,"<="&DATE(I19,12,31)) -> 0.085550833
B20: 45352 | C20: 0.07052 | D20: 0.07062 | E20: 0.07103 | F20: 0.07006 | G20: -0.0037 | I20: =I19+1 -> 2015 | J20: =AVERAGEIFS($C$3:$C$332,$B$3:$B$332,">="&DATE(I20,1,1),$B$3:$B$332,"<="&DATE(I20,12,31)) -> 0.077501667
B21: 45323 | C21: 0.07078 | D21: 0.07129 | E21: 0.0714 | F21: 0.07021 | G21: -0.0092 | I21: =I20+1 -> 2016 | J21: =AVERAGEIFS($C$3:$C$332,$B$3:$B$332,">="&DATE(I21,1,1),$B$3:$B$332,"<="&DATE(I21,12,31)) -> 0.071738333
B22: 45292 | C22: 0.07144 | D22: 0.07207 | E22: 0.07239 | F22: 0.07134 | G22: -0.0045 | I22: =I21+1 -> 2017 | J22: =AVERAGEIFS($C$3:$C$332,$B$3:$B$332,">="&DATE(I22,1,1),$B$3:$B$332,"<="&DATE(I22,12,31)) -> 0.0674725
B23: 45261 | C23: 0.07176 | D23: 0.07293 | E23: 0.07298 | F23: 0.07147 | G23: -0.0142 | I23: =I22+1 -> 2018 | J23: =AVERAGEIFS($C$3:$C$332,$B$3:$B$332,">="&DATE(I23,1,1),$B$3:$B$332,"<="&DATE(I23,12,31)) -> 0.077189167
B24: 45231 | C24: 0.07279 | D24: 0.07376 | E24: 0.07376 | F24: 0.07194 | G24: -0.0098 | I24: =I23+1 -> 2019 | J24: =AVERAGEIFS($C$3:$C$332,$B$3:$B$332,">="&DATE(I24,1,1),$B$3:$B$332,"<="&DATE(I24,12,31)) -> 0.069185
... B29: 45078 | C29: 0.0711 | D29: 0.07019 | E29: 0.07117 | F29: 0.06963 | G29: 0.0173 | I29: =I28+1 -> 2024 | J29: =AVERAGEIFS($C$3:$C$332,$B$3:$B$332,">="&DATE(I29,1,1),$B$3:$B$332,"<="&DATE(I29,12,31)) -> 0.06946
B30: 45047 | C30: 0.06989 | D30: 0.07135 | E30: 0.07138 | F30: 0.06947 | G30: -0.0178
B31: 45017 | C31: 0.07116 | D31: 0.0737 | E31: 0.0737 | F31: 0.07077 | G31: -0.0272
B32: 44986 | C32: 0.07315 | D32: 0.07468 | E32: 0.07473 | F32: 0.0728 | G32: -0.019
B33: 44958 | C33: 0.07457 | D33: 0.07416 | E33: 0.07465 | F33: 0.07245 | G33: 0.0155
B34: 44927 | C34: 0.07343 | D34: 0.07346 | E34: 0.07407 | F34: 0.07266 | G34: 0.0022
B35: 44896 | C35: 0.07327 | D35: 0.07255 | E35: 0.07344 | F35: 0.07181 | G35: 0.0065
B36: 44866 | C36: 0.0728 | D36: 0.07435 | E36: 0.07497 | F36: 0.07235 | G36: -0.0222
B37: 44835 | C37: 0.07445 | D37: 0.07403 | E37: 0.07541 | F37: 0.07361 | G37: 0.0064
B38: 44805 | C38: 0.07398 | D38: 0.0723 | E38: 0.07423 | F38: 0.07106 | G38: 0.0292
B39: 44774 | C39: 0.07188 | D39: 0.07357 | E39: 0.07366 | F39: 0.0711 | G39: -0.018
B40: 44743 | C40: 0.0732 | D40: 0.07427 | E40: 0.07475 | F40: 0.07255 | G40: -0.0174
B41: 44713 | C41: 0.0745 | D41: 0.07437 | E41: 0.07617 | F41: 0.07365 | G41: 0.0047
... B332: 35855 | C332: 0.12086 | D332: 0.12086 | E332: 0.12086 | F332: 0.12086 | G332: -0.0527
B334: Source: Investing.com

Sheet ErpHistorical
B2: Years | C2: Implied ERP of India
B3: 1997 | C3: 0.02
B4: 1998 | C4: 0.02 | E4: Average Implied ERP- | F4: 15 years | G4: =AVERAGE(C16:C30) -> 0.02312
B5: 1999 | C5: 0.0197
B6: 2000 | C6: 0.0199 | E6: Average Implied ERP- | F6: 7 years | G6: =AVERAGE(C24:C30) -> 0.018028571
B7: 2001 | C7: 0.055
B8: 2002 | C8: 0.0492 | E8: Average Implied ERP- | F8: 5 years | G8: =AVERAGE(C26:C30) -> 0.01684
B9: 2003 | C9: 0.0708
B10: 2004 | C10: 0.0456 | E10: Average Implied ERP- | F10: Latest | G10: =C31 -> 0.0167
B11: 2005 | C11: 0.0486
B12: 2006 | C12: 0.0318
B13: 2007 | C13: 0.0308
B14: 2008 | C14: 0.0411
B15: 2009 | C15: 0.0322
B16: 2010 | C16: 0.027
B17: 2011 | C17: 0.0366
B18: 2012 | C18: 0.0365
B19: 2013 | C19: 0.0282
B20: 2014 | C20: 0.0236
B21: 2015 | C21: 0.0256
B22: 2016 | C22: 0.0238
... B31: 2025 | C31: 0.0167
B33: Source: Market Premia

Sheet 2025-BBData
B2: Industry name | C2: Number of firms | D2: Dividends | E2: Dividends + Buybacks | F2: Buybacks | G2: Buybacks%Dividend
B3: Advertising | C3: 26 | D3: 2.11 | E3: 4.45 | F3: =IF((D3>E3),0,(E3-D3)) -> 2.34 | G3: =IFERROR(F3/D3,0) -> 1.1090047
B4: Aerospace/Defense | C4: 20 | D4: 585.91 | E4: 585.91 | F4: =IF((D4>E4),0,(E4-D4)) -> 0 | G4: =IFERROR(F4/D4,0) -> 0
B5: Air Transport | C5: 4 | D5: 0.96 | E5: 0 | F5: =IF((D5>E5),0,(E5-D5)) -> 0 | G5: =IFERROR(F5/D5,0) -> 0
B6: Apparel | C6: 366 | D6: 411.77 | E6: 549.28 | F6: =IF((D6>E6),0,(E6-D6)) -> 137.51 | G6: =IFERROR(F6/D6,0) -> 0.33394856
B7: Auto & Truck | C7: 14 | D7: 3123.5 | E7: 3735.56 | F7: =IF((D7>E7),0,(E7-D7)) -> 612.06 | G7: =IFERROR(F7/D7,0) -> 0.19595326 | I7: Mean | J7: =AVERAGE(G3:G96) -> 0.36153207
B8: Auto Parts | C8: 117 | D8: 585 | E8: 637.28 | F8: =IF((D8>E8),0,(E8-D8)) -> 52.28 | G8: =IFERROR(F8/D8,0) -> 0.089367521 | I8: Trimmed Mean 10% | J8: =TRIMMEAN(G3:G96,0.5) -> 0.014556565
B9: Bank (Money Center) | C9: 35 | D9: 6540.41 | E9: 6540.41 | F9: =IF((D9>E9),0,(E9-D9)) -> 0 | G9: =IFERROR(F9/D9,0) -> 0
B10: Banks (Regional) | C10: 6 | D10: 69.42 | E10: 69.42 | F10: =IF((D10>E10),0,(E10-D10)) -> 0 | G10: =IFERROR(F10/D10,0) -> 0
B11: Beverage (Alcoholic) | C11: 19 | D11: 129.83 | E11: 129.83 | F11: =IF((D11>E11),0,(E11-D11)) -> 0 | G11: =IFERROR(F11/D11,0) -> 0
B12: Beverage (Soft) | C12: 5 | D12: 40.58 | E12: 0 | F12: =IF((D12>E12),0,(E12-D12)) -> 0 | G12: =IFERROR(F12/D12,0) -> 0
B13: Broadcasting | C13: 19 | D13: 91.33 | E13: 79.8 | F13: =IF((D13>E13),0,(E13-D13)) -> 0 | G13: =IFERROR(F13/D13,0) -> 0
B14: Brokerage & Investment Banking | C14: 176 | D14: 225.76 | E14: 229.32 | F14: =IF((D14>E14),0,(E14-D14)) -> 3.56 | G14: =IFERROR(F14/D14,0) -> 0.015768958
B15: Building Materials | C15: 57 | D15: 90.73 | E15: 128.63 | F15: =IF((D15>E15),0,(E15-D15)) -> 37.9 | G15: =IFERROR(F15/D15,0) -> 0.41772291
B16: Business & Consumer Services | C16: 72 | D16: 235.69 | E16: 246.02 | F16: =IF((D16>E16),0,(E16-D16)) -> 10.33 | G16: =IFERROR(F16/D16,0) -> 0.043828758
B17: Cable TV | C17: 8 | D17: 5.77 | E17: 5.77 | F17: =IF((D17>E17),0,(E17-D17)) -> 0 | G17: =IFERROR(F17/D17,0) -> 0
B18: Chemical (Basic) | C18: 145 | D18: 524.32 | E18: 436.97 | F18: =IF((D18>E18),0,(E18-D18)) -> 0 | G18: =IFERROR(F18/D18,0) -> 0
B19: Chemical (Diversified) | C19: 9 | D19: 147.04 | E19: 154.42 | F19: =IF((D19>E19),0,(E19-D19)) -> 7.38 | G19: =IFERROR(F19/D19,0) -> 0.050190424
B20: Chemical (Specialty) | C20: 184 | D20: 951.08 | E20: 1168.79 | F20: =IF((D20>E20),0,(E20-D20)) -> 217.71 | G20: =IFERROR(F20/D20,0) -> 0.22890819
... B98: Total Market (without financials) | C98: 4162 | D98: 45519 | E98: 51097.3 | F98: =IF((D98>E98),0,(E98-D98)) -> 5578.3 | G98: =IFERROR(F98/D98,0) -> 0.12254883
B100: Source: Damodaran
